hpe3par_sdk/__init__.py
hpe3par_sdk/client.py
hpe3par_sdk/exceptions.py
hpe3par_sdk/models.py
hpe3par_sdk-3.0.dist-info/METADATA
hpe3par_sdk-3.0.dist-info/WHEEL
hpe3par_sdk-3.0.dist-info/licenses/LICENSE
hpe3par_sdk-3.0.dist-info/RECORD
