Metadata-Version: 2.4
Name: hpe3par-sdk
Version: 3.0
Summary: HPE Alletra MP, 9000, Primera and 3PAR Software Development Kit for Python
Author-email: Raghavendra Tilay <raghavendra-uddhav.tilay@hpe.com>
License-File: LICENSE
Classifier: Development Status :: 5 - Production/Stable
Classifier: Environment :: Web Environment
Classifier: Intended Audience :: Developers
Classifier: License :: OSI Approved :: Apache Software License
Classifier: Operating System :: OS Independent
Classifier: Programming Language :: Python
Classifier: Programming Language :: Python :: 2.7
Classifier: Programming Language :: Python :: 3.8
Classifier: Topic :: Internet :: WWW/HTTP
